README.md
setup.py
getrpimodel/__init__.py
getrpimodel/__main__.py
getrpimodel.egg-info/PKG-INFO
getrpimodel.egg-info/SOURCES.txt
getrpimodel.egg-info/dependency_links.txt
getrpimodel.egg-info/top_level.txt