Metadata-Version: 2.1
Name: getrpimodel
Version: 0.1.21
Summary: Get Raspberry Pi model Name(eg: A, B, B+...)
Home-page: https://github.com/UedaTakeyuki/getrpimodel
Author: Takeyuki UEDA
Author-email: gde00107@nifty.com
License: MIT
Keywords: IoT,Raspberry Pi,model,revision
Platform: UNKNOWN
Classifier: Development Status :: 4 - Beta
Classifier: Programming Language :: Python
Classifier: Topic :: Terminals
